torchsummaryX/__init__.py
torchsummaryX/test.py
torchsummaryX/torchsummaryX.py
torchsummaryX-1.2.0.dist-info/METADATA
torchsummaryX-1.2.0.dist-info/WHEEL
torchsummaryX-1.2.0.dist-info/top_level.txt
torchsummaryX-1.2.0.dist-info/RECORD
